double_buffer_shared_memory/__init__.py
double_buffer_shared_memory/double_buffered_shared_memory_manager.py
double_buffer_shared_memory/infos.py
double_buffer_shared_memory/log_messages.py
double_buffer_shared_memory_manager-1.0.3.dist-info/LICENSE
double_buffer_shared_memory_manager-1.0.3.dist-info/METADATA
double_buffer_shared_memory_manager-1.0.3.dist-info/WHEEL
double_buffer_shared_memory_manager-1.0.3.dist-info/top_level.txt
double_buffer_shared_memory_manager-1.0.3.dist-info/RECORD
