Metadata-Version: 2.1
Name: double-buffer-shared-memory-manager
Version: 1.0.3
Summary: Package for communication with shared memory using double buffer
Home-page: https://github.com/m-ghiani/DOUBLE_BUFFER_SHARED_MEMORY_MANAGER
Author: Massimo Ghiani
Author-email: m.ghiani@gmail.com
License: MIT
Classifier: Development Status :: 5 - Production/Stable
Classifier: Operating System :: OS Independent
Classifier: Intended Audience :: Developers
Classifier: License :: OSI Approved :: MIT License
Classifier: Programming Language :: Python :: 3.10
Classifier: Programming Language :: Python :: 3.11
Classifier: Programming Language :: Python :: 3.12
Requires-Python: >=3.10
License-File: LICENSE
Requires-Dist: colorlog >=6.8.0
Requires-Dist: numpy >=1.26.2
Requires-Dist: readerwriterlock >=1.0.9
